hlupik
